README.md
setup.py
py_elf_structs/__init__.py
py_elf_structs/__main__.py
py_elf_structs.egg-info/PKG-INFO
py_elf_structs.egg-info/SOURCES.txt
py_elf_structs.egg-info/dependency_links.txt
py_elf_structs.egg-info/requires.txt
py_elf_structs.egg-info/top_level.txt
py_elf_structs/lib/__init__.py
py_elf_structs/lib/generate_structs.py
py_elf_structs/lib/loader.py
py_elf_structs/lib/parser.py
py_elf_structs/lib/structs.py
py_elf_structs/lib/utils.py