Metadata-Version: 1.0
Name: py-elf-structs
Version: 1.4.2
Summary: Python package to extract struct and type information from dwarf and build python cstructs
Home-page: https://github.com/jonatanSh/py-elf-structs
Author: Jonathan Shimon
Author-email: jonatanshimon@gmail.com
License: MIT License
Platform: UNKNOWN
